Workbook

Sheet Premissas
A1: Premissas do Modelo Financeiro - Nosso Momento
A3: Métrica / Premissa | B3: Valor | C3: Descrição
A4: Mensalidade VIP (R$) | B4: 14.99 | C4: Preço do plano recorrente mensal por casal
A5: Taxa de Usuários Ativos (MAU) | B5: 0.5 | C5: Percentual da base total que interage mensalmente no app
A6: Conversão VIP sobre Ativos | B6: 0.15 | C6: Percentual de usuários ativos que assinam o plano VIP
A7: Taxa das Lojas (App Store/Play Store) | B7: 0.15 | C7: Comissão cobrada pelas lojas de aplicativos sobre as vendas
A8: Receita por Parceiro/Patrocinador (R$) | B8: 300 | C8: Valor fixo mensal pago por cada marca/patrocinador plugado
A9: Custo Legal Mensal (R$) | B9: 65 | C9: Custos fixos com contabilidade, taxas jurídicas e manutenção legal
A10: Custo de Aquisição de Cliente - CAC (R$) | B10: 25 | C10: Investimento estimado de marketing para adquirir 1 usuário VIP
A11: Tempo de Permanência Médio - Lifetime | B11: 12 | C11: Meses que um casal permanece como assinante VIP do app
A12: Valor do Tempo de Vida - LTV (R$) | B12: =B4*B11 | C12: Receita total gerada por um cliente antes do Churn (Mensalidade * Lifetime)
A13: Relação de Viabilidade (LTV / CAC) | B13: =B12/B10 | C13: Métrica de saúde digital. O ideal de mercado para viabilidade é ser > 3.0x
A14: Custo Médio p/ Micro-Influenciador (R$) | B14: 250 | C14: Custo médio por ação (Reels + Stories) para perfis de casais (10k-30k seg.)

Sheet Planejamento Financeiro
A1: Demonstração do Resultado (DRE) e Fluxo de Caixa - 24 Meses
A3: Conta / Mês | B3: M1 | C3: M2 | D3: M3 | E3: M4 | F3: M5 | G3: M6 | H3: M7 | I3: M8 | J3: M9 | K3: M10 | L3: M11 | M3: M12 | N3: M13 | O3: M14 | P3: M15 | Q3: M16 | R3: M17 | S3: M18 | T3: M19 | U3: M20 | V3: M21 | W3: M22 | X3: M23 | Y3: M24
A4: Base Total (Qtde) | B4: 50 | C4: 65 | D4: 80 | E4: 100 | F4: 120 | G4: 145 | H4: 175 | I4: 210 | J4: 250 | K4: 290 | L4: 330 | M4: 375 | N4: 420 | O4: 470 | P4: 5375 | Q4: 5500 | R4: 5650 | S4: 5800 | T4: 6000 | U4: 6200 | V4: 6500 | W4: 6800 | X4: 7100 | Y4: 7500
A5: Base Ativa (Qtde) | B5: =ROUND(B4*Premissas!$B$5,0) | C5: =ROUND(C4*Premissas!$B$5,0) | D5: =ROUND(D4*Premissas!$B$5,0) | E5: =ROUND(E4*Premissas!$B$5,0) | F5: =ROUND(F4*Premissas!$B$5,0) | G5: =ROUND(G4*Premissas!$B$5,0) | H5: =ROUND(H4*Premissas!$B$5,0) | I5: =ROUND(I4*Premissas!$B$5,0) | ... Y5: =ROUND(Y4*Premissas!$B$5,0)
A6: Usuários VIP (Qtde) | B6: =ROUND(B5*Premissas!$B$6,0) | C6: =ROUND(C5*Premissas!$B$6,0) | D6: =ROUND(D5*Premissas!$B$6,0) | E6: =ROUND(E5*Premissas!$B$6,0) | F6: =ROUND(F5*Premissas!$B$6,0) | G6: =ROUND(G5*Premissas!$B$6,0) | H6: =ROUND(H5*Premissas!$B$6,0) | I6: =ROUND(I5*Premissas!$B$6,0) | ... Y6: =ROUND(Y5*Premissas!$B$6,0)
A7: Parceiros Ativos (Qtde) | B7: 0 | C7: 0 | D7: 0 | E7: 0 | F7: 0 | G7: 0 | H7: 2 | I7: 2 | J7: 2 | K7: 3 | L7: 3 | M7: 3 | N7: 3 | O7: 4 | P7: 4 | Q7: 4 | R7: 4 | S7: 4 | T7: 4 | U7: 4 | V7: 4 | W7: 4 | X7: 4 | Y7: 4
A8: (+) Receita VIP (R$) | B8: =B6*Premissas!$B$4 | C8: =C6*Premissas!$B$4 | D8: =D6*Premissas!$B$4 | E8: =E6*Premissas!$B$4 | F8: =F6*Premissas!$B$4 | G8: =G6*Premissas!$B$4 | H8: =H6*Premissas!$B$4 | I8: =I6*Premissas!$B$4 | ... Y8: =Y6*Premissas!$B$4
A9: (+) Receita Parceiros (R$) | B9: =B7*Premissas!$B$8 | C9: =C7*Premissas!$B$8 | D9: =D7*Premissas!$B$8 | E9: =E7*Premissas!$B$8 | F9: =F7*Premissas!$B$8 | G9: =G7*Premissas!$B$8 | H9: =H7*Premissas!$B$8 | I9: =I7*Premissas!$B$8 | ... Y9: =Y7*Premissas!$B$8
A10: (=) Receita Bruta (R$) | B10: =SUM(B8:B9) | C10: =SUM(C8:C9) | D10: =SUM(D8:D9) | E10: =SUM(E8:E9) | F10: =SUM(F8:F9) | G10: =SUM(G8:G9) | H10: =SUM(H8:H9) | I10: =SUM(I8:I9) | ... Y10: =SUM(Y8:Y9)
A11: (-) Taxas Loja (R$) | B11: =-1*(B10*Premissas!$B$7) | C11: =-1*(C10*Premissas!$B$7) | D11: =-1*(D10*Premissas!$B$7) | E11: =-1*(E10*Premissas!$B$7) | F11: =-1*(F10*Premissas!$B$7) | G11: =-1*(G10*Premissas!$B$7) | H11: =-1*(H10*Premissas!$B$7) | I11: =-1*(I10*Premissas!$B$7) | ... Y11: =-1*(Y10*Premissas!$B$7)
A12: (=) Receita Líquida (R$) | B12: =B10+B11 | C12: =C10+C11 | D12: =D10+D11 | E12: =E10+E11 | F12: =F10+F11 | G12: =G10+G11 | H12: =H10+H11 | I12: =I10+I11 | ... Y12: =Y10+Y11
A13: (-) Infraestrutura (R$) | B13: -150 | C13: -150 | D13: -150 | E13: -150 | F13: -150 | G13: -150 | H13: -150 | I13: -150 | J13: -150 | K13: -200 | L13: -200 | M13: -250 | N13: -250 | O13: -300 | P13: -800 | Q13: -800 | R13: -800 | S13: -800 | T13: -1000 | U13: -1000 | V13: -1000 | W13: -1200 | X13: -1200 | Y13: -1200
A14: (-) Tráfego Pago (R$) | B14: -500 | C14: -600 | D14: -700 | E14: -800 | F14: -900 | G14: -1000 | H14: -1000 | I14: -1100 | J14: -1210 | K14: -1331 | L14: -1464 | M14: -1610 | N14: -1771 | O14: -1948 | P14: -2000 | Q14: -2000 | R14: -2000 | S14: -2000 | T14: -2000 | U14: -2000 | V14: -2000 | W14: -2000 | X14: -2000 | Y14: -2000
A15: (-) Micro-influenciadores (R$) | B15: 0 | C15: 0 | D15: -250 | E15: -250 | F15: -250 | G15: -250 | H15: -250 | I15: -250 | J15: -250 | K15: -250 | L15: -250 | M15: -250 | N15: -500 | O15: -500 | P15: -500 | Q15: -500 | R15: -500 | S15: -500 | T15: -500 | U15: -500 | V15: -500 | W15: -500 | X15: -500 | Y15: -500
A16: (-) Custos Legais (R$) | B16: =-1*Premissas!$B$9 | C16: =-1*Premissas!$B$9 | D16: =-1*Premissas!$B$9 | E16: =-1*Premissas!$B$9 | F16: =-1*Premissas!$B$9 | G16: =-1*Premissas!$B$9 | H16: =-1*Premissas!$B$9 | I16: =-1*Premissas!$B$9 | ... Y16: =-1*Premissas!$B$9
A17: (=) EBITDA (R$) | B17: =B12+SUM(B13:B16) | C17: =C12+SUM(C13:C16) | D17: =D12+SUM(D13:D16) | E17: =E12+SUM(E13:E16) | F17: =F12+SUM(F13:F16) | G17: =G12+SUM(G13:G16) | H17: =H12+SUM(H13:H16) | I17: =I12+SUM(I13:I16) | ... Y17: =Y12+SUM(Y13:Y16)
A18: (=) Margem EBITDA (%) | B18: =B17/B12 | C18: =C17/C12 | D18: =D17/D12 | E18: =E17/E12 | F18: =F17/F12 | G18: =G17/G12 | H18: =H17/H12 | I18: =I17/I12 | ... Y18: =Y17/Y12
A19: (-) Impostos (IRPJ/CSLL) (R$) | B19: =IF(B17>0,-B17*0.15,0) | C19: =IF(C17>0,-C17*0.15,0) | D19: =IF(D17>0,-D17*0.15,0) | E19: =IF(E17>0,-E17*0.15,0) | F19: =IF(F17>0,-F17*0.15,0) | G19: =IF(G17>0,-G17*0.15,0) | H19: =IF(H17>0,-H17*0.15,0) | I19: =IF(I17>0,-I17*0.15,0) | ... Y19: =IF(Y17>0,-Y17*0.15,0)
A20: (+/-) Resultado Financeiro (R$) | B20: 0 | C20: 0 | D20: 0 | E20: 0 | F20: 0 | G20: 0 | H20: 0 | I20: 0 | J20: 0 | K20: 0 | L20: 0 | M20: 0 | N20: 0 | O20: 0 | P20: 0 | Q20: 0 | R20: 0 | S20: 0 | T20: 0 | U20: 0 | V20: 0 | W20: 0 | X20: 0 | Y20: 0
A21: (=) LUCRO LÍQUIDO (R$) | B21: =B17+B19+B20 | C21: =C17+C19+C20 | D21: =D17+D19+D20 | E21: =E17+E19+E20 | F21: =F17+F19+F20 | G21: =G17+G19+G20 | H21: =H17+H19+H20 | I21: =I17+I19+I20 | ... Y21: =Y17+Y19+Y20
A22: (=) Margem Líquida (%) | B22: =B21/B12 | C22: =C21/C12 | D22: =D21/D12 | E22: =E21/E12 | F22: =F21/F12 | G22: =G21/G12 | H22: =H21/H12 | I22: =I21/I12 | ... Y22: =Y21/Y12
A24: ANÁLISE DE FLUXO DE CAIXA
A25: (+) Investimento Inicial / Aporte (R$) | B25: 12000 | C25: 0 | D25: 0 | E25: 0 | F25: 0 | G25: 0 | H25: 0 | I25: 0 | J25: 0 | K25: 0 | L25: 0 | M25: 0 | N25: 0 | O25: 0 | P25: 0 | Q25: 0 | R25: 0 | S25: 0 | T25: 0 | U25: 0 | V25: 0 | W25: 0 | X25: 0 | Y25: 0
A26: (+) Fluxo de Caixa Mensal (R$) | B26: =B21 | C26: =C21 | D26: =D21 | E26: =E21 | F26: =F21 | G26: =G21 | H26: =H21 | I26: =I21 | ... Y26: =Y21
A27: (=) Saldo de Caixa Acumulado (R$) | B27: =B25+B26 | C27: =B27+C25+C26 | D27: =C27+D25+D26 | E27: =D27+E25+E26 | F27: =E27+F25+F26 | G27: =F27+G25+G26 | H27: =G27+H25+H26 | I27: =H27+I25+I26 | J27: =I27+J25+J26 | ... Y27: =X27+Y25+Y26

Sheet Indicadores de Viabilidade
A1: Análise de Viabilidade Financeira (Métricas Avançadas)
A3: Métrica Financeira | B3: Resultado | C3: Critério de Aceitação / Status
A4: Taxa Mínima de Atratividade (TMA Mensal) | B4: 0.01 | C4: Taxa de desconto referencial de mercado (~1.0% am)
A5: Valor Presente Líquido (VPL) | B5: =VPL(B4, 'Planejamento Financeiro'!B26:Y26) - 12000 | C5: Se for > 0, o projeto compensa o investimento inicial e gera riqueza extra
A6: Taxa Interna de Retorno (TIR Mensal) | B6: =IRR('Planejamento Financeiro'!B26:Y26) | C6: Rentabilidade interna do projeto. Deve ser maior que a TMA
A7: Taxa Interna de Retorno (TIR Anualizada) | B7: =(1+B6)^12-1 | C7: TIR convertida para base anual para fins de comparação com a taxa Selic/CDI
A8: Ponto de Equilíbrio Operacional (Break-Even) | B8: Mês 15 | C8: Mês em que as receitas recorrentes superam os custos mensais pela primeira vez
A9: Payback Simples (Retorno do Investimento) | B9: Mês 16 | C9: Mês em que o saldo acumulado de caixa cobre o aporte inicial reduzido
